skrt/__init__.py
skrt/application.py
skrt/core.py
skrt/dicom_writer.py
skrt/dose.py
skrt/image.py
skrt/multi.py
skrt/patient.py
skrt/registration.py
skrt/segmentation.py
skrt/simulation.py
skrt/structures.py
skrt/better_viewer/__init__.py
skrt/better_viewer/options.py
skrt/data/elastix_parameter_files/BE_BSpline05.txt
skrt/data/elastix_parameter_files/MI_Affine.txt
skrt/data/elastix_parameter_files/MI_BSpline05.txt
skrt/data/elastix_parameter_files/MI_BSpline15.txt
skrt/data/elastix_parameter_files/MI_BSpline30.txt
skrt/data/elastix_parameter_files/MI_Rigid.txt
skrt/data/elastix_parameter_files/MI_Translation.txt
skrt/data/niftyreg_parameter_files/Affine.txt
skrt/data/niftyreg_parameter_files/BE_BSpline05.txt
skrt/data/niftyreg_parameter_files/NMI_BSpline05.txt
skrt/data/niftyreg_parameter_files/NMI_BSpline15.txt
skrt/data/niftyreg_parameter_files/NMI_BSpline30.txt
skrt/data/niftyreg_parameter_files/Rigid.txt
skrt/viewer/__init__.py
skrt/viewer/core.py
skrt/viewer/viewer.py
scikit_rt-0.8.2.dist-info/LICENSE
scikit_rt-0.8.2.dist-info/METADATA
scikit_rt-0.8.2.dist-info/WHEEL
scikit_rt-0.8.2.dist-info/top_level.txt
scikit_rt-0.8.2.dist-info/RECORD
