Metadata-Version: 2.1
Name: scikit-rt
Version: 0.8.2
Summary: Toolkit for analysis of radiotherapy data
Home-page: https://github.com/scikit-rt/scikit-rt
Author: H. Pullen, K. Harrison
Author-email: scikit-rt@hep.phy.cam.ac.uk
Project-URL: Bug Tracker, https://github.com/scikit-rt/scikit-rt/issues
Classifier: Programming Language :: Python :: 3
Classifier: License :: OSI Approved :: GNU General Public License (GPL)
Classifier: Operating System :: OS Independent
Classifier: Intended Audience :: Science/Research
Requires-Python: >=3.8
License-File: LICENSE
Requires-Dist: MarkupSafe==2.1.1
Requires-Dist: PyWavelets==1.3.0
Requires-Dist: Send2Trash==1.8.0
Requires-Dist: SimpleITK==2.1.1.2
Requires-Dist: anyio==3.6.1
Requires-Dist: appnope==0.1.3
Requires-Dist: argon2-cffi==21.3.0
Requires-Dist: argon2-cffi-bindings==21.2.0
Requires-Dist: asttokens==2.0.7
Requires-Dist: attrs==22.1.0
Requires-Dist: babel==2.10.3
Requires-Dist: backcall==0.2.0
Requires-Dist: beautifulsoup4==4.11.1
Requires-Dist: bleach==5.0.1
Requires-Dist: cffi==1.15.1
Requires-Dist: charset-normalizer==2.1.0
Requires-Dist: cycler==0.11.0
Requires-Dist: debugpy==1.6.2
Requires-Dist: decorator==5.1.1
Requires-Dist: defusedxml==0.7.1
Requires-Dist: entrypoints==0.4
Requires-Dist: executing==0.9.1
Requires-Dist: fastjsonschema==2.16.1
Requires-Dist: fonttools==4.34.4
Requires-Dist: idna==3.3
Requires-Dist: imageio==2.21.1
Requires-Dist: importlib-metadata==4.12.0
Requires-Dist: importlib-resources==5.9.0
Requires-Dist: iniconfig==1.1.1
Requires-Dist: ipykernel==6.15.1
Requires-Dist: ipython==8.4.0
Requires-Dist: ipython-genutils==0.2.0
Requires-Dist: ipywidgets==7.7.1
Requires-Dist: jedi==0.17.2
Requires-Dist: jinja2==3.0.3
Requires-Dist: json5==0.9.9
Requires-Dist: jsonschema==4.9.1
Requires-Dist: jupyter==1.0.0
Requires-Dist: jupyter-client==7.3.4
Requires-Dist: jupyter-console==6.4.4
Requires-Dist: jupyter-core==4.11.1
Requires-Dist: jupyter-server==1.18.1
Requires-Dist: jupyterlab==3.4.5
Requires-Dist: jupyterlab-pygments==0.2.2
Requires-Dist: jupyterlab-server==2.15.0
Requires-Dist: jupyterlab-widgets==1.1.1
Requires-Dist: kiwisolver==1.4.4
Requires-Dist: lxml==5.1.1
Requires-Dist: matplotlib==3.5.2
Requires-Dist: matplotlib-inline==0.1.3
Requires-Dist: mistune==0.8.4
Requires-Dist: nbclassic==0.4.3
Requires-Dist: nbclient==0.6.6
Requires-Dist: nbconvert==6.5.2
Requires-Dist: nbformat==5.4.0
Requires-Dist: nest-asyncio==1.5.5
Requires-Dist: networkx==2.8.5
Requires-Dist: nibabel==4.0.1
Requires-Dist: notebook==6.4.12
Requires-Dist: notebook-shim==0.1.0
Requires-Dist: numpy==1.23.1
Requires-Dist: packaging==21.3
Requires-Dist: pandas==1.4.3
Requires-Dist: pandocfilters==1.5.0
Requires-Dist: parso==0.7.1
Requires-Dist: pexpect==4.8.0
Requires-Dist: pickleshare==0.7.5
Requires-Dist: pillow==9.2.0
Requires-Dist: pkgutil-resolve-name==1.3.10
Requires-Dist: pluggy==1.0.0
Requires-Dist: prometheus-client==0.14.1
Requires-Dist: prompt-toolkit==3.0.30
Requires-Dist: psutil==5.9.1
Requires-Dist: ptyprocess==0.7.0
Requires-Dist: pure-eval==0.2.2
Requires-Dist: py==1.11.0
Requires-Dist: pycparser==2.21
Requires-Dist: pydicom==2.3.0
Requires-Dist: pygments==2.12.0
Requires-Dist: pyparsing==3.0.9
Requires-Dist: pyrsistent==0.18.1
Requires-Dist: pytest==7.1.2
Requires-Dist: python-dateutil==2.8.2
Requires-Dist: python-gdcm==3.0.14
Requires-Dist: pytz==2022.1
Requires-Dist: pyzmq==23.2.0
Requires-Dist: qtconsole==5.3.1
Requires-Dist: qtpy==2.2.0
Requires-Dist: requests==2.28.1
Requires-Dist: scikit-image==0.19.3
Requires-Dist: scipy==1.9.0
Requires-Dist: shapely==2.0.1
Requires-Dist: six==1.16.0
Requires-Dist: sniffio==1.2.0
Requires-Dist: soupsieve==2.3.2.post1
Requires-Dist: stack-data==0.3.0
Requires-Dist: terminado==0.15.0
Requires-Dist: tifffile==2022.8.8
Requires-Dist: tinycss2==1.1.1
Requires-Dist: tomli==2.0.1
Requires-Dist: tomli-w==1.0.0
Requires-Dist: tornado==6.2
Requires-Dist: traitlets==5.3.0
Requires-Dist: urllib3==1.26.11
Requires-Dist: wcwidth==0.2.5
Requires-Dist: webencodings==0.5.1
Requires-Dist: websocket-client==1.3.3
Requires-Dist: widgetsnbextension==3.6.1
Requires-Dist: zipp==3.8.1
Requires-Dist: atomicwrites==1.4.0; os_name == "nt"
Requires-Dist: pywinpty==2.0.10; os_name == "nt"
